koshka/__init__.py
koshka/httpls.py
koshka/kot.py
koshka/kote.py
koshka/kssh.py
koshka/s3.py
koshka/tests.py
koshka/version.py
koshka-0.9.dist-info/METADATA
koshka-0.9.dist-info/WHEEL
koshka-0.9.dist-info/entry_points.txt
koshka-0.9.dist-info/top_level.txt
koshka-0.9.dist-info/RECORD
