Metadata-Version: 2.1
Name: koshka
Version: 0.9
Summary: GNU cat over the network with autocompletion
Home-page: https://github.com/mpenkov/koshka
Author: Michael Penkov
Author-email: m@penkov.dev
License: UNKNOWN
Keywords: cat,s3,autocomplete
Platform: UNKNOWN
Requires-Dist: argcomplete
Requires-Dist: smart-open[http,s3]
